{
    "timestamp": "2026-04-17 21:03:25",
    "fonte": "B3 / InfoMoney",
    "vertices": [
        {
            "du": 10,
            "taxa": 14.63
        },
        {
            "du": 31,
            "taxa": 14.459
        },
        {
            "du": 53,
            "taxa": 14.378
        },
        {
            "du": 76,
            "taxa": 14.285
        },
        {
            "du": 97,
            "taxa": 14.19
        },
        {
            "du": 119,
            "taxa": 14.11
        },
        {
            "du": 141,
            "taxa": 14.03
        },
        {
            "du": 162,
            "taxa": 13.97
        },
        {
            "du": 185,
            "taxa": 13.9
        },
        {
            "du": 206,
            "taxa": 13.815
        },
        {
            "du": 226,
            "taxa": 13.76
        },
        {
            "du": 249,
            "taxa": 13.72
        },
        {
            "du": 314,
            "taxa": 13.535
        },
        {
            "du": 336,
            "taxa": 13.44
        },
        {
            "du": 380,
            "taxa": 13.38
        },
        {
            "du": 401,
            "taxa": 13.315
        },
        {
            "du": 423,
            "taxa": 13.23
        },
        {
            "du": 446,
            "taxa": 13.255
        },
        {
            "du": 511,
            "taxa": 13.2
        },
        {
            "du": 576,
            "taxa": 13.17
        },
        {
            "du": 641,
            "taxa": 13.155
        },
        {
            "du": 663,
            "taxa": 13.13
        },
        {
            "du": 685,
            "taxa": 13.12
        },
        {
            "du": 706,
            "taxa": 13.15
        },
        {
            "du": 771,
            "taxa": 13.16
        },
        {
            "du": 836,
            "taxa": 13.185
        },
        {
            "du": 901,
            "taxa": 13.195
        },
        {
            "du": 946,
            "taxa": 13.185
        },
        {
            "du": 967,
            "taxa": 13.215
        },
        {
            "du": 1031,
            "taxa": 13.215
        },
        {
            "du": 1096,
            "taxa": 13.25
        },
        {
            "du": 1162,
            "taxa": 13.23
        },
        {
            "du": 1228,
            "taxa": 13.285
        },
        {
            "du": 1292,
            "taxa": 13.305
        },
        {
            "du": 1357,
            "taxa": 13.31
        },
        {
            "du": 1423,
            "taxa": 13.325
        },
        {
            "du": 1489,
            "taxa": 13.36
        },
        {
            "du": 1751,
            "taxa": 13.4
        },
        {
            "du": 2011,
            "taxa": 13.405
        },
        {
            "du": 2271,
            "taxa": 13.405
        },
        {
            "du": 2532,
            "taxa": 13.395
        },
        {
            "du": 2794,
            "taxa": 13.425
        },
        {
            "du": 3055,
            "taxa": 13.42
        }
    ]
}